{
"Cheirogaleus andysabini": "Montagne d'Ambre dwarf lemur",
"Cheirogaleus crossleyi": "Furry-eared dwarf lemur",
"Cheirogaleus lavasoensis": "Lavasoa dwarf lemur",
"Cheirogaleus major": "Greater dwarf lemur",
"Cheirogaleus medius": "Fat-tailed dwarf lemur",
"Cheirogaleus minusculus": "Lesser iron-gray dwarf lemur",
"Cheirogaleus sibreei": "Sibree's dwarf lemur",
"Microcebus arnholdi": "Arnhold's mouse lemur",
"Microcebus berthae": "Madame Berthe's mouse lemur",
"Microcebus bongolavensis": "Bongolava mouse lemur",
"Microcebus boraha": "Boraha mouse lemur",
"Microcebus danfossi": "Danfoss' mouse lemur",
"Microcebus ganzhorni": "Ganzhorn's mouse lemur",
"Microcebus griseorufus": "Reddish-gray mouse lemur",
"Microcebus jollyae": "Jolly's mouse lemur",
"Microcebus lehilahytsara": "Goodman's mouse lemur",
"Microcebus macarthurii": "MacArthur's mouse lemur",
"Microcebus mamiratra": "Claire's mouse lemur",
"Microcebus margotmarshae": "Margot Marsh's mouse lemur",
"Microcebus marohita": "Marohita mouse lemur",
"Microcebus mittermeieri": "Mittermeier's mouse lemur",
"Microcebus gerpi": "Gerp's mouse lemur",
"Microcebus murinus": "Gray mouse lemur",
"Microcebus myoxinus": "Pygmy mouse lemur",
"Microcebus sambiranensis": "Sambirano mouse lemur",
"Microcebus simmonsi": "Simmons' mouse lemur",
"Microcebus ravelobensis": "Golden-brown mouse lemur",
"Microcebus rufus": "Brown mouse lemur",
"Microcebus tanosi": "Anosy mouse lemur",
"Microcebus tavaratra": "Northern rufous mouse lemur",
"Mirza coquereli": "Coquerel's giant mouse lemur or Coquerel's mouse lemur",
"Mirza zaza": "Northern giant mouse lemur",
"Allocebus trichotis": "Hairy-eared dwarf lemur",
"Phaner electromontis": "Amber Mountain fork-marked lemur",
"Phaner furcifer": "Masoala fork-marked lemur",
"Phaner pallescens": "Pale fork-marked lemur",
"Phaner parienti": "Pariente's fork-marked lemur",
"Lemur catta": "Ring-tailed lemur",
"Eulemur albifrons": "White-headed lemur",
"Eulemur cinereiceps": "Gray-headed lemur",
"Eulemur collaris": "Collared brown lemur",
"Eulemur coronatus": "Crowned lemur",
"Eulemur flavifrons": "Blue-eyed black lemur",
"Eulemur fulvus": "Common brown lemur",
"Eulemur macaco": "Black lemur",
"Eulemur mongoz": "Mongoose lemur",
"Eulemur rubriventer": "Red-bellied lemur",
"Eulemur rufifrons": "Red-fronted lemur",
"Eulemur rufus": "Red lemur",
"Eulemur sanfordi": "Sanford's brown lemur",
"Hapalemur alaotrensis": "Lac Alaotra bamboo lemur",
"Hapalemur aureus": "Golden bamboo lemur",
"Hapalemur griseus": "Eastern lesser bamboo lemur",
"Hapalemur meridionalis": "Southern lesser bamboo lemur",
"Hapalemur occidentalis": "Western lesser bamboo lemur",
"Prolemur simus": "Greater bamboo lemur",
"Varecia rubra": "Red ruffed lemur",
"Varecia variegata": "Black-and-white ruffed lemur",
"Lepilemur aeeclis": "AEECL's sportive lemur",
"Lepilemur ahmansoni": "Ahmanson's sportive lemur",
"Lepilemur ankaranensis": "Ankarana sportive lemur",
"Lepilemur betsileo": "Betsileo sportive lemur",
"Lepilemur dorsalis": "Gray-backed sportive lemur",
"Lepilemur edwardsi": "Milne-Edwards' sportive lemur",
"Lepilemur fleuretae": "Fleurete's sportive lemur",
"Lepilemur grewcocki": "Grewcock's sportive lemur",
"Lepilemur hubbardi": "Hubbard's sportive lemur",
"Lepilemur hollandorum": "Holland's sportive lemur",
"Lepilemur jamesi": "James' sportive lemur",
"Lepilemur leucopus": "White-footed sportive lemur",
"Lepilemur microdon": "Small-toothed sportive lemur",
"Lepilemur milanoii": "Daraina sportive lemur",
"Lepilemur mittermeieri": "Mittermeier's sportive lemur",
"Lepilemur mustelinus": "Weasel sportive lemur",
"Lepilemur otto": "Otto's sportive lemur",
"Lepilemur petteri": "Petter's sportive lemur",
"Lepilemur randrianasoli": "Randrianasolo's sportive lemur",
"Lepilemur ruficaudatus": "Red-tailed sportive lemur",
"Lepilemur sahamalazensis": "Sahamalaza sportive lemur",
"Lepilemur scottorum": "Scott's sportive lemur",
"Lepilemur seali": "Seal's sportive lemur",
"Lepilemur septentrionalis": "Northern sportive lemur",
"Lepilemur tymerlachsoni": "Hawks' sportive lemur",
"Lepilemur wrighti": "Wright's sportive lemur",
"Indri indri": "Indri",
"Avahi betsileo": "Betsileo woolly lemur",
"Avahi cleesei": "Bemaraha woolly lemur",
"Avahi laniger": "Eastern woolly lemur",
"Avahi meridionalis": "Southern woolly lemur",
"Avahi mooreorum": "Moore's woolly lemur",
"Avahi occidentalis": "Western woolly lemur",
"Avahi peyrierasi": "Peyrieras' woolly lemur",
"Avahi ramanantsoavani": "Ramanantsoavana's woolly lemur",
"Avahi unicolor": "Sambirano woolly lemur",
"Propithecus candidus": "Silky sifaka",
"Propithecus coquereli": "Coquerel's sifaka",
"Propithecus coronatus": "Crowned sifaka",
"Propithecus deckenii": "Von der Decken's sifaka",
"Propithecus diadema": "Diademed sifaka",
"Propithecus edwardsi": "Milne-Edwards' sifaka",
"Propithecus perrieri": "Perrier's sifaka",
"Propithecus tattersalli": "Golden-crowned sifaka",
"Propithecus verreauxi": "Verreaux's sifaka",
"Daubentonia madagascariensis": "Aye-aye",
"Arctocebus aureus": "Golden angwantibo",
"Arctocebus calabarensis": "Calabar angwantibo",
"Perodicticus potto": "Potto",
"Pseudopotto martini": "False potto",
"Loris lydekkerianus": "Gray slender loris",
"Loris tardigradus": "red slender loris",
"Nycticebus bengalensis": "Bengal slow loris",
"Nycticebus coucang": "Sunda slow loris",
"Nycticebus javanicus": "Javan slow loris",
"Nycticebus menagensis": "Philippine slow loris",
"Nycticebus pygmaeus": "Pygmy slow loris",
"Galago gallarum": "Somali bushbaby",
"Galago matschiei": "Dusky bushbaby",
"Galago moholi": "Mohol bushbaby",
"Galago senegalensis": "Senegal bushbaby",
"Galagoides cocos": "Kenya coast galago",
"Galagoides demidovii": "Prince Demidoff's bushbaby",
"Galagoides granti": "Grant's bushbaby",
"Galagoides nyasae": "Malawi bushbaby",
"Galagoides orinus": "Uluguru bushbaby",
"Galagoides rondoensis": "Rondo dwarf galago",
"Galagoides thomasi": "Thomas's bushbaby",
"Galagoides zanzibaricus": "Zanzibar bushbaby",
"Otolemur crassicaudatus": "Brown greater galago",
"Otolemur garnettii": "Northern greater galago",
"Otolemur monteiri": "Silvery greater galago",
"Euoticus elegantulus": "Southern needle-clawed bushbaby",
"Euoticus pallidus": "Northern needle-clawed bushbaby",
"Sciurocheirus alleni": "Bioko Allen's bushbaby",
"Sciurocheirus cameronensis": "Cross River bushbaby",
"Sciurocheirus gabonensis": "Gabon bushbaby",
"Carlito syrichta": "Philippine tarsier",
"Cephalopachus bancanus": "Horsfield's tarsier",
"Tarsius dentatus": "Dian's tarsier",
"Tarsius lariang": "Lariang tarsier",
"Tarsius pelengensis": "Peleng tarsier",
"Tarsius pumilus": "Pygmy tarsier",
"Tarsius sangirensis": "Sangihe tarsier",
"Tarsius tarsier": "Spectral tarsier",
"Tarsius tumpara": "Siau Island tarsier",
"Tarsius wallacei": "Wallace's tarsier",
"Callithrix aurita": "Buffy-tufted marmoset",
"Callithrix flaviceps": "Buffy-headed marmoset",
"Callithrix geoffroyi": "White-headed marmoset",
"Callithrix jacchus": "Common marmoset",
"Callithrix kuhlii": "Wied's marmoset",
"Callithrix penicillata": "Black-tufted marmoset",
"Mico acariensis": "Rio Acari marmoset",
"Mico argentatus": "Silvery marmoset",
"Mico chrysoleuca": "Gold-and-white marmoset",
"Mico emiliae": "Emilia's marmoset",
"Mico humeralifera": "Santarem marmoset",
"Mico intermedia": "Hershkovitz's marmoset",
"Mico leucippe": "White marmoset",
"Mico nigriceps": "Black-headed marmoset",
"Mico manicorensis": "Manicore marmoset",
"Mico marcai": "Marca's marmoset",
"Mico mauesi": "Maués marmoset",
"Mico melanura": "Black-tailed marmoset",
"Mico rondoni": "Rondon's marmoset",
"Mico saterei": "Satéré marmoset",
"Callibella humilis": "Roosmalens' dwarf marmoset",
"Cebuella pygmaea": "Pygmy marmoset",
"Leontopithecus caissara": "Superagui lion tamarin",
"Leontopithecus chrysomelas": "Golden-headed lion tamarin",
"Leontopithecus chrysopygus": "Black lion tamarin",
"Leontopithecus rosalia": "Golden lion tamarin",
"Saguinus bicolor": "Pied tamarin",
"Saguinus fuscicollis": "Brown-mantled tamarin",
"Saguinus geoffroyi": "Geoffroy's tamarin",
"Saguinus graellsi": "Graells's tamarin",
"Saguinus imperator": "Emperor tamarin",
"Saguinus inustus": "Mottle-faced tamarin",
"Saguinus labiatus": "White-lipped tamarin",
"Saguinus leucopus": "White-footed tamarin",
"Saguinus martinsi": "Martins's tamarin",
"Saguinus melanoleucus": "White-mantled tamarin",
"Saguinus midas": "Red-handed tamarin",
"Saguinus mystax": "Moustached tamarin",
"Saguinus niger": "Black tamarin",
"Saguinus nigricollis": "Black-mantled tamarin",
"Saguinus oedipus": "Cotton-top tamarin or Pinché tamarin",
"Saguinus pileatus": "Red-capped tamarin",
"Saguinus tripartitus": "Golden-mantled tamarin",
"Callimico goeldii": "Goeldi's marmoset",
"Cebus albifrons": "White-fronted capuchin",
"Cebus capucinus": "White-headed capuchin",
"Cebus kaapori": "Kaapori capuchin",
"Cebus olivaceus": "Wedge-capped capuchin",
"Sapajus apella": "Tufted capuchin",
"Sapajus cay": "Azaras's capuchin",
"Sapajus flavius": "Blond capuchin",
"Sapajus libidinosus": "Black-striped capuchin",
"Sapajus macrocephalus": "Large-headed capuchin",
"Sapajus nigritus": "Black capuchin",
"Sapajus robustus": "Crested capuchin",
"Sapajus xanthosternos": "Golden-bellied capuchin",
"Saimiri boliviensis": "Black-capped squirrel monkey",
"Saimiri oerstedii": "Central American squirrel monkey",
"Saimiri sciureus": "Common squirrel monkey",
"Saimiri ustus": "Bare-eared squirrel monkey",
"Saimiri vanzolinii": "Black squirrel monkey",
"Aotus azarae": "Azara's night monkey",
"Aotus brumbacki": "Brumback's night monkey",
"Aotus griseimembra": "Gray-handed night monkey",
"Aotus jorgehernandezi": "Hernández-Camacho's night monkey",
"Aotus lemurinus": "Gray-bellied night monkey",
"Aotus miconax": "Peruvian night monkey",
"Aotus nancymae": "Nancy Ma's night monkey",
"Aotus nigriceps": "Black-headed night monkey",
"Aotus trivirgatus": "Three-striped night monkey",
"Aotus vociferans": "Spix's night monkey",
"Aotus zonalis": "Panamanian night monkey",
"Callicebus baptista": "Baptista Lake titi",
"Callicebus barbarabrownae": "Barbara Brown's titi",
"Callicebus bernhardi": "Prince Bernhard's titi",
"Callicebus brunneus": "Brown titi",
"Callicebus caligatus": "Chestnut-bellied titi",
"Callicebus cinerascens": "Ashy black titi",
"Callicebus coimbrai": "Coimbra Filho's titi",
"Callicebus cupreus": "Coppery titi",
"Callicebus discolor": "White-tailed titi",
"Callicebus donacophilus": "White-eared titi",
"Callicebus dubius": "Hershkovitz's titi",
"Callicebus hoffmannsi": "Hoffmanns's titi",
"Callicebus melanochir": "Coastal black-handed titi",
"Callicebus miltoni": "Milton's titi",
"Callicebus modestus": "Rio Beni titi",
"Callicebus moloch": "Red-bellied titi",
"Callicebus nigrifrons": "Black-fronted titi",
"Callicebus oenanthe": "Rio Mayo titi",
"Callicebus olallae": "Ollala brothers' titi",
"Callicebus ornatus": "Ornate titi",
"Callicebus pallescens": "White-coated titi",
"Callicebus personatus": "Atlantic titi",
"Callicebus stephennashi": "Stephen Nash's titi",
"Callicebus lucifer": "Lucifer titi",
"Callicebus lugens": "Black titi",
"Callicebus medemi": "Colombian black-handed titi",
"Callicebus purinus": "Rio Purus titi",
"Callicebus regulus": "Red-headed titi",
"Callicebus torquatus": "Collared titi",
"Callicebus aureipalatii": "Madidi titi",
"Callicebus caquetensis": "Caquetá titi",
"Callicebus vieirai": "Vieira's titi",
"Pithecia aequatorialis": "Equatorial saki",
"Pithecia albicans": "White-footed saki",
"Pithecia chrysocephala": "Golden-faced saki",
"Pithecia irrorata": "Rio Tapajós saki",
"Pithecia milleri": "Miller's saki",
"Pithecia monachus": "Monk saki",
"Pithecia napensis": "Napo saki",
"Pithecia pithecia": "White-faced saki",
"Pithecia vanzolinii": "Vanzolini's bald-faced saki",
"Chiropotes albinasus": "White-nosed saki",
"Chiropotes chiropotes": "Red-backed bearded saki",
"Chiropotes israelita": "Brown-backed bearded saki",
"Chiropotes satanas": "Black bearded saki",
"Chiropotes utahickae": "Uta Hick's bearded saki",
"Cacajao ayresii": "Aracá uakari",
"Cacajao calvus": "Bald uakari",
"Cacajao hosomi": "Neblina uakari",
"Cacajao melanocephalus": "Golden-backed uakari",
"Alouatta arctoidea": "Ursine howler",
"Alouatta belzebul": "Red-handed howler",
"Alouatta caraya": "Black howler",
"Alouatta coibensis": "Coiba Island howler",
"Alouatta discolor": "Spix's red-handed howler",
"Alouatta guariba": "Brown howler",
"Alouatta juara": "Juruá red howler",
"Alouatta macconnelli": "Guyanan red howler",
"Alouatta nigerrima": "Amazon black howler",
"Alouatta palliata": "Mantled howler",
"Alouatta pigra": "Guatemalan black howler",
"Alouatta puruensis": "Purus red howler",
"Alouatta sara": "Bolivian red howler",
"Alouatta seniculus": "Venezuelan red howler",
"Alouatta ululata": "Maranhão red-handed howler",
"Ateles belzebuth": "White-bellied spider monkey",
"Ateles chamek": "Peruvian spider monkey",
"Ateles fusciceps": "Black-headed spider monkey",
"Ateles geoffroyi": "Geoffroy's spider monkey",
"Ateles hybridus": "Brown spider monkey",
"Ateles marginatus": "White-cheeked spider monkey",
"Ateles paniscus": "Red-faced spider monkey",
"Brachyteles arachnoides": "Southern muriqui",
"Brachyteles hypoxanthus": "Northern muriqui",
"Lagothrix cana": "Gray woolly monkey",
"Lagothrix lagotricha": "Brown woolly monkey",
"Lagothrix lugens": "Colombian woolly monkey",
"Lagothrix poeppigii": "Silvery woolly monkey",
"Oreonax flavicauda": "Yellow-tailed woolly monkey",
"Allenopithecus nigroviridis": "Allen's swamp monkey",
"Miopithecus ogouensis": "Gabon talapoin",
"Miopithecus talapoin": "Angolan talapoin",
"Erythrocebus patas": "Patas monkey",
"Chlorocebus aethiops": "Grivet",
"Chlorocebus cynosuros": "Malbrouck",
"Chlorocebus djamdjamensis": "Bale Mountains vervet",
"Chlorocebus sabaeus": "Green monkey",
"Chlorocebus tantalus": "Tantalus monkey",
"Chlorocebus pygerythrus": "Vervet monkey",
"Cercopithecus albogularis": "Sykes' monkey",
"Cercopithecus ascanius": "Red-tailed monkey",
"Cercopithecus campbelli": "Campbell's mona monkey",
"Cercopithecus cephus": "Moustached guenon",
"Cercopithecus denti": "Dent's mona monkey",
"Cercopithecus diana": "Diana monkey",
"Cercopithecus doggetti": "Silver monkey",
"Cercopithecus dryas": "Dryas monkey or Salongo monkey",
"Cercopithecus erythrogast": "White-throated guenon",
"Cercopithecus hamlyni": "Hamlyn's monkey or owl-faced monkey",
"Cercopithecus erythrotis": "Red-eared guenon",
"Cercopithecus kandti": "Golden monkey",
"Cercopithecus lhoesti": "L'Hoest's monkey",
"Cercopithecus lomamiensis": "Lesula",
"Cercopithecus lowei": "Lowe's mona monkey",
"Cercopithecus mitis": "Blue monkey",
"Cercopithecus mona": "Mona monkey",
"Cercopithecus neglectus": "De Brazza's monkey",
"Cercopithecus nictitans": "Greater spot-nosed monkey",
"Cercopithecus petaurista": "Lesser spot-nosed monkey",
"Cercopithecus pogonias": "Crested mona monkey",
"Cercopithecus preussi": "Preuss's monkey",
"Cercopithecus roloway": "Roloway monkey",
"Cercopithecus sclateri": "Sclater's guenon",
"Cercopithecus solatus": "Sun-tailed monkey",
"Cercopithecus wolfi": "Wolf's mona monkey",
"Macaca arctoides": "Stump-tailed macaque",
"Macaca assamensis": "Assam macaque",
"Macaca cyclopis": "Formosan rock macaque",
"Macaca fuscata": "Japanese macaque",
"Macaca fascicularis": "Crab-eating macaque",
"Macaca hecki": "Heck's macaque",
"Macaca leonina": "Northern pig-tailed macaque",
"Macaca leucogenys": "White-cheeked macaque",
"Macaca maura": "Moor macaque",
"Macaca mulatta": "Rhesus macaque",
"Macaca munzala": "Arunachal macaque",
"Macaca nemestrina": "Southern pig-tailed macaque",
"Macaca nigra": "Celebes crested macaque",
"Macaca nigrescens": "Gorontalo macaque",
"Macaca ochreata": "Booted macaque",
"Macaca pagensis": "Pagai Island macaque",
"Macaca radiata": "Bonnet macaque",
"Macaca siberu": "Siberut macaque",
"Macaca silenus": "Lion-tailed macaque",
"Macaca sinica": "Toque macaque",
"Macaca sylvanus": "Barbary macaque",
"Macaca thibetana": "Tibetan macaque",
"Macaca tonkeana": "Tonkean macaque",
"Lophocebus albigena": "Grey-cheeked mangabey",
"Lophocebus aterrimus": "Black crested mangabey",
"Lophocebus johnstoni": "Johnston's mangabey",
"Lophocebus opdenboschi": "Opdenbosch's mangabey",
"Lophocebus osmani": "Osman Hill's mangabey",
"Lophocebus ugandae": "Uganda mangabey",
"Rungwecebus kipunji": "Kipunji",
"Papio anubis": "Olive baboon",
"Papio cynocephalus": "Yellow baboon",
"Papio hamadryas": "Hamadryas baboon",
"Papio papio": "Guinea baboon",
"Papio ursinus": "Chacma baboon",
"Theropithecus gelada": "Gelada",
"Cercocebus agilis": "Agile mangabey",
"Cercocebus atys": "Sooty mangabey",
"Cercocebus chrysogaster": "Golden-bellied mangabey",
"Cercocebus galeritus": "Tana River mangabey",
"Cercocebus sanjei": "Sanje mangabey",
"Cercocebus torquatus": "Collared mangabey",
"Mandrillus sphinx": "Mandrill",
"Mandrillus leucophaeus": "Drill",
"Colobus angolensis": "Angola colobus",
"Colobus guereza": "Mantled guereza",
"Colobus polykomos": "King colobus",
"Colobus satanas": "Black colobus",
"Colobus vellerosus": "Ursine colobus",
"Procolobus badius": "Western red colobus",
"Procolobus epieni": "Niger Delta red colobus",
"Procolobus foai": "Central African red colobus",
"Procolobus gordonorum": "Udzungwa red colobus",
"Procolobus kirkii": "Zanzibar red colobus",
"Procolobus pennantii": "Pennant's colobus",
"Procolobus preussi": "Preuss's red colobus",
"Procolobus rufomitratus": "Tana River red colobus",
"Procolobus tephrosceles": "Ugandan red colobus",
"Procolobus tholloni": "Thollon's red colobus",
"Procolobus verus": "Olive colobus",
"Semnopithecus ajax": "Kashmir gray langur",
"Semnopithecus dussumieri": "Southern plains gray langur",
"Semnopithecus entellus": "Northern plains gray langur",
"Semnopithecus hector": "Tarai gray langur",
"Semnopithecus hypoleucos": "Black-footed gray langur",
"Semnopithecus priam": "Tufted gray langur",
"Semnopithecus schistaceus": "Nepal gray langur",
"Trachypithecus auratus": "Javan lutung",
"Trachypithecus barbei": "Tenasserim lutung",
"Trachypithecus cristatus": "Silvery lutung or silvered leaf monkey",
"Trachypithecus delacouri": "Delacour's langur",
"Trachypithecus francoisi": "François' langur",
"Trachypithecus geei": "Gee's golden langur",
"Trachypithecus germaini": "Indochinese lutung",
"Trachypithecus hatinhensis": "Hatinh langur",
"Trachypithecus ebenus": "Indochinese black langur",
"Trachypithecus johnii": "Nilgiri langur",
"Trachypithecus laotum": "Laotian langur",
"Trachypithecus obscurus": "Dusky leaf monkey",
"Trachypithecus phayrei": "Phayre's leaf monkey",
"Trachypithecus pileatus": "Capped langur",
"Trachypithecus poliocephalus": "White-headed langur",
"Trachypithecus shortridgei": "Shortridge's langur",
"Trachypithecus vetulus": "Purple-faced langur",
"Presbytis comata": "Javan surili",
"Presbytis chrysomelas": "Sarawak surili",
"Presbytis femoralis": "Banded surili",
"Presbytis frontata": "White-fronted surili",
"Presbytis hosei": "Hose's langur",
"Presbytis melalophos": "Sumatran surili",
"Presbytis natunae": "Natuna Island surili",
"Presbytis potenziani": "Mentawai langur or joja",
"Presbytis rubicunda": "Maroon leaf monkey",
"Presbytis siamensis": "White-thighed surili",
"Presbytis thomasi": "Thomas's langur",
"Pygathrix cinerea": "Gray-shanked douc",
"Pygathrix nemaeus": "Red-shanked douc",
"Pygathrix nigripes": "Black-shanked douc",
"Rhinopithecus avunculus": "Tonkin snub-nosed monkey",
"Rhinopithecus bieti": "Black snub-nosed monkey",
"Rhinopithecus brelichi": "Gray snub-nosed monkey",
"Rhinopithecus roxellana": "Golden snub-nosed monkey",
"Rhinopithecus strykeri": "Myanmar snub-nosed monkey",
"Nasalis larvatus": "Proboscis monkey",
"Simias concolor": "Pig-tailed langur",
"Hylobates agilis": "Agile gibbon",
"Hylobates albibarbis": "Bornean white-bearded gibbon",
"Hylobates klossii": "Kloss's gibbon",
"Hylobates lar": "Lar gibbon or white-handed gibbon",
"Hylobates moloch": "Silvery gibbon",
"Hylobates muelleri": "Müller's Bornean gibbon",
"Hylobates pileatus": "Pileated gibbon",
"Hoolock hoolock": "Western hoolock gibbon",
"Hoolock leuconedys": "Eastern hoolock gibbon",
"Symphalangus syndactylus": "Siamang",
"Nomascus annamensis": "Northern buffed-cheeked gibbon",
"Nomascus concolor": "black crested gibbon",
"Nomascus gabriellae": "Yellow-cheeked gibbon",
"Nomascus hainanus": "Hainan black crested gibbon",
"Nomascus leucogenys": "Northern white-cheeked gibbon",
"Nomascus nasutus": "Eastern black crested gibbon",
"Nomascus siki": "Southern white-cheeked gibbon",
"Pongo abelii": "Sumatran orangutan",
"Pongo pygmaeus": "Bornean orangutan",
"Gorilla beringei": "Eastern gorilla",
"Gorilla gorilla": "Western gorilla",
"Gorilla gorilla gorilla": "Western gorilla",
"Pan paniscus": "Bonobo or pygmy chimpanzee",
"Pan troglodytes": "Common chimpanzee",
"Homo sapiens": "Human"
}